massive/massivizer.py
massive/vanessa.py
massive/discord/discord_massive.py
massive/discord/discord_massive_vanessa.py
massive/util/swap_chars.py
massive.py-0.5.3.dist-info/LICENSE
massive.py-0.5.3.dist-info/METADATA
massive.py-0.5.3.dist-info/WHEEL
massive.py-0.5.3.dist-info/top_level.txt
massive.py-0.5.3.dist-info/RECORD
