Metadata-Version: 2.1
Name: massive.py
Version: 0.5.3
Summary: Utilities for converting text to massive text, especially on Discord.
Home-page: https://github.com/TheRandomLabs/massive.py
Author: TheRandomLabs
Author-email: therandomlabsinc@gmail.com
License: MIT
Project-URL: Bug Tracker, https://github.com/TheRandomLabs/massive.py/issues
Project-URL: Source Code, https://github.com/TheRandomLabs/massive.py
Keywords: massive text discord
Platform: UNKNOWN
Classifier: Development Status :: 4 - Beta
Classifier: Intended Audience :: Developers
Classifier: License :: OSI Approved :: MIT License
Classifier: Operating System :: OS Independent
Classifier: Programming Language :: Python :: 3.7
Requires-Dist: emoji
